pyVHDLModel/Association.py
pyVHDLModel/Base.py
pyVHDLModel/Common.py
pyVHDLModel/Concurrent.py
pyVHDLModel/Declaration.py
pyVHDLModel/DesignUnit.py
pyVHDLModel/Exception.py
pyVHDLModel/Expression.py
pyVHDLModel/IEEE.py
pyVHDLModel/Instantiation.py
pyVHDLModel/Interface.py
pyVHDLModel/Name.py
pyVHDLModel/Namespace.py
pyVHDLModel/Object.py
pyVHDLModel/PSLModel.py
pyVHDLModel/Predefined.py
pyVHDLModel/Regions.py
pyVHDLModel/STD.py
pyVHDLModel/Sequential.py
pyVHDLModel/Subprogram.py
pyVHDLModel/Symbol.py
pyVHDLModel/Type.py
pyVHDLModel/__init__.py
pyVHDLModel/py.typed
pyvhdlmodel-0.33.0.dist-info/licenses/LICENSE.md
pyvhdlmodel-0.33.0.dist-info/METADATA
pyvhdlmodel-0.33.0.dist-info/WHEEL
pyvhdlmodel-0.33.0.dist-info/top_level.txt
pyvhdlmodel-0.33.0.dist-info/RECORD
