Metadata-Version: 2.4
Name: pyVHDLModel
Version: 0.33.0
Summary: An abstract VHDL language model.
Home-page: https://GitHub.com/VHDL/pyVHDLModel
Author: Patrick Lehmann
Author-email: Paebbels@gmail.com
License: Apache-2.0
Project-URL: Documentation, https://VHDL.GitHub.io/pyVHDLModel
Project-URL: Source Code, https://GitHub.com/VHDL/pyVHDLModel
Project-URL: Issue Tracker, https://GitHub.com/VHDL/pyVHDLModel/issues
Keywords: Python3 VHDL Language Model Abstract
Classifier: Operating System :: OS Independent
Classifier: Intended Audience :: Developers
Classifier: Topic :: Utilities
Classifier: Topic :: Scientific/Engineering :: Electronic Design Automation (EDA)
Classifier: Topic :: Software Development :: Code Generators
Classifier: Topic :: Software Development :: Compilers
Classifier: License :: OSI Approved :: Apache Software License
Classifier: Programming Language :: Python :: 3 :: Only
Classifier: Programming Language :: Python :: 3.11
Classifier: Programming Language :: Python :: 3.12
Classifier: Programming Language :: Python :: 3.13
Classifier: Programming Language :: Python :: 3.14
Classifier: Development Status :: 4 - Beta
Requires-Python: >=3.11
License-File: LICENSE.md
Requires-Dist: pyTooling~=8.8
Provides-Extra: doc
Requires-Dist: sphinx_design~=0.6; extra == "doc"
Requires-Dist: sphinx-copybutton>=0.5; extra == "doc"
Requires-Dist: autoapi>=2.0.1; extra == "doc"
Requires-Dist: sphinx_reports~=0.9; extra == "doc"
Requires-Dist: docutils_stubs~=0.0.22; extra == "doc"
Requires-Dist: sphinxcontrib-mermaid~=1.0; extra == "doc"
Requires-Dist: sphinx_autodoc_typehints~=3.5; extra == "doc"
Requires-Dist: sphinx~=8.2; extra == "doc"
Requires-Dist: docutils~=0.21; extra == "doc"
Requires-Dist: sphinx_rtd_theme~=3.0; extra == "doc"
Requires-Dist: pyTooling~=8.8; extra == "doc"
Provides-Extra: test
Requires-Dist: mypy[reports]~=1.18; extra == "test"
Requires-Dist: Coverage~=7.11; extra == "test"
Requires-Dist: pytest~=9.0; extra == "test"
Requires-Dist: pytest-cov~=7.0; extra == "test"
Requires-Dist: typing_extensions~=4.15; extra == "test"
Requires-Dist: lxml<7.0,>=5.4; extra == "test"
Requires-Dist: pyTooling~=8.8; extra == "test"
Provides-Extra: all
Requires-Dist: sphinx_design~=0.6; extra == "all"
Requires-Dist: mypy[reports]~=1.18; extra == "all"
Requires-Dist: Coverage~=7.11; extra == "all"
Requires-Dist: autoapi>=2.0.1; extra == "all"
Requires-Dist: sphinx_reports~=0.9; extra == "all"
Requires-Dist: pytest~=9.0; extra == "all"
Requires-Dist: docutils_stubs~=0.0.22; extra == "all"
Requires-Dist: sphinxcontrib-mermaid~=1.0; extra == "all"
Requires-Dist: pyTooling~=8.8; extra == "all"
Requires-Dist: sphinx_autodoc_typehints~=3.5; extra == "all"
Requires-Dist: pytest-cov~=7.0; extra == "all"
Requires-Dist: typing_extensions~=4.15; extra == "all"
Requires-Dist: sphinx~=8.2; extra == "all"
Requires-Dist: lxml<7.0,>=5.4; extra == "all"
Requires-Dist: docutils~=0.21; extra == "all"
Requires-Dist: sphinx_rtd_theme~=3.0; extra == "all"
Requires-Dist: sphinx-copybutton>=0.5; extra == "all"
Dynamic: author
Dynamic: author-email
Dynamic: classifier
Dynamic: description
Dynamic: description-content-type
Dynamic: home-page
Dynamic: keywords
Dynamic: license
Dynamic: license-file
Dynamic: project-url
Dynamic: provides-extra
Dynamic: requires-dist
Dynamic: requires-python
Dynamic: summary
